LICENSE
MANIFEST.in
README.md
setup.py
gmplmagic/__init__.py
gmplmagic/gmplmagic.py
gmplmagic.egg-info/PKG-INFO
gmplmagic.egg-info/SOURCES.txt
gmplmagic.egg-info/dependency_links.txt
gmplmagic.egg-info/requires.txt
gmplmagic.egg-info/top_level.txt