Metadata-Version: 1.0
Name: gmplmagic
Version: 0.1.4
Summary: GMPL/MathProg magics for IPython/Jupyter
Home-page: https://github.com/nelsonuhan/gmplmagic
Author: Nelson Uhan
Author-email: nelson@uhan.me
License: GNU GPLv3
Platform: UNKNOWN
